Phemus/Aequitas_Fully_Directed_Sklearn.py
Phemus/Aequitas_Random_Sklearn.py
Phemus/Aequitas_Semi_Directed_Sklearn.py
Phemus/Dataset.py
Phemus/Generate_Sklearn_Classifier.py
Phemus/Retrain_Sklearn.py
Phemus/Run_Aequitas.py
Phemus/Sklearn_Estimation.py
Phemus/__init__.py
Phemus/mpFully_Direct.py
Phemus/utils.py
Phemus-1.0.0.dist-info/METADATA
Phemus-1.0.0.dist-info/WHEEL
Phemus-1.0.0.dist-info/top_level.txt
Phemus-1.0.0.dist-info/RECORD
