Metadata-Version: 2.1
Name: Phemus
Version: 1.0.0
Summary: A Python library aims to determine the Fairness of machine learning datasets
Home-page: UNKNOWN
Author: Yunping Wang
Author-email: <wangj6@carleton.edu>
License: UNKNOWN
Keywords: python,machine learning fairness
Platform: UNKNOWN
Classifier: Development Status :: 3 - Alpha
Classifier: Intended Audience :: Education
Classifier: Programming Language :: Python :: 3
Classifier: Operating System :: MacOS :: MacOS X
Classifier: Operating System :: Microsoft :: Windows
